<?xml version="1.0" encoding="utf-8" ?>
<Grid Name = "Medium 7x47 KenKen" Index="6">
  <Cages>    
    <Cage TargetValue="6" Operation="Subtract">
      <Cells>
        <Cell Row="0" Column="0" />
        <Cell Row="1" Column="0" />
      </Cells>
    </Cage>
    <Cage TargetValue="1" Operation="Subtract">
      <Cells>
        <Cell Row="0" Column="1" />
        <Cell Row="1" Column="1" />
      </Cells>
    </Cage>
    <Cage TargetValue="1" Operation="Subtract">
      <Cells>
        <Cell Row="0" Column="2" />
        <Cell Row="0" Column="3" />
      </Cells>
    </Cage>
    <Cage TargetValue="126" Operation="Multiply">
      <Cells>
        <Cell Row="0" Column="4" />
        <Cell Row="1" Column="4" />
        <Cell Row="2" Column="4" />
      </Cells>
    </Cage>
    <Cage TargetValue="4" Operation="Subtract">
      <Cells>
        <Cell Row="0" Column="5" />
        <Cell Row="0" Column="6" />
      </Cells>
    </Cage>
    <Cage TargetValue="10" Operation="Add">
      <Cells>
        <Cell Row="1" Column="2" />
        <Cell Row="1" Column="3" />
        <Cell Row="2" Column="2" />
      </Cells>
    </Cage>
    <Cage TargetValue="1" Operation="Subtract">
      <Cells>
        <Cell Row="1" Column="5" />
        <Cell Row="1" Column="6" />
      </Cells>
    </Cage>
    <Cage TargetValue="13" Operation="Add">
      <Cells>
        <Cell Row="2" Column="0" />
        <Cell Row="2" Column="1" />
        <Cell Row="3" Column="0" />
      </Cells>
    </Cage>
    <Cage TargetValue="40" Operation="Multiply">
      <Cells>
        <Cell Row="2" Column="3" />
        <Cell Row="3" Column="3" />
        <Cell Row="3" Column="4" />
      </Cells>
    </Cage>
    <Cage TargetValue="3" Operation="Divide">
      <Cells>
        <Cell Row="2" Column="5" />
        <Cell Row="2" Column="6" />
      </Cells>
    </Cage>
    <Cage TargetValue="7" Operation="None">
      <Cells>
        <Cell Row="3" Column="1" />
      </Cells>
    </Cage>
    <Cage TargetValue="2" Operation="Subtract">
      <Cells>
        <Cell Row="3" Column="2" />
        <Cell Row="4" Column="2" />
      </Cells>
    </Cage>
    <Cage TargetValue="8" Operation="Add">
      <Cells>
        <Cell Row="3" Column="5" />
        <Cell Row="3" Column="6" />
        <Cell Row="4" Column="5" />
      </Cells>
    </Cage>
    <Cage TargetValue="2" Operation="Divide">
      <Cells>
        <Cell Row="4" Column="0" />
        <Cell Row="4" Column="1" />
      </Cells>
    </Cage>
    <Cage TargetValue="42" Operation="Multiply">
      <Cells>
        <Cell Row="4" Column="3" />
        <Cell Row="5" Column="3" />
      </Cells>
    </Cage>
    <Cage TargetValue="4" Operation="None">
      <Cells>
        <Cell Row="4" Column="4" />
      </Cells>
    </Cage>
    <Cage TargetValue="11" Operation="Add">
      <Cells>
        <Cell Row="4" Column="6" />
        <Cell Row="5" Column="6" />        
      </Cells>
    </Cage>
    <Cage TargetValue="1" Operation="Subtract">
      <Cells>
        <Cell Row="5" Column="0" />
        <Cell Row="6" Column="0" />
      </Cells>
    </Cage>
    <Cage TargetValue="30" Operation="Multiply">
      <Cells>
        <Cell Row="5" Column="1" />
        <Cell Row="6" Column="1" />
        <Cell Row="6" Column="2" />
      </Cells>
    </Cage>
    <Cage TargetValue="6" Operation="None">
      <Cells>
        <Cell Row="5" Column="2" />
      </Cells>
    </Cage>
    <Cage TargetValue="2" Operation="Divide">
      <Cells>
        <Cell Row="5" Column="4" />
        <Cell Row="5" Column="5" />
      </Cells>
    </Cage>
    <Cage TargetValue="17" Operation="Add">
      <Cells>
        <Cell Row="6" Column="3" />
        <Cell Row="6" Column="4" />
        <Cell Row="6" Column="5" />
        <Cell Row="6" Column="6" />
      </Cells>
    </Cage>
  </Cages>
</Grid>